tangelo/__init__.py
tangelo/_version.py
tangelo/molecule_library.py
tangelo/algorithms/__init__.py
tangelo/algorithms/electronic_structure_solver.py
tangelo/algorithms/classical/__init__.py
tangelo/algorithms/classical/ccsd_solver.py
tangelo/algorithms/classical/fci_solver.py
tangelo/algorithms/classical/mp2_solver.py
tangelo/algorithms/classical/tests/__init__.py
tangelo/algorithms/classical/tests/test_ccsd_solver.py
tangelo/algorithms/classical/tests/test_fci_solver.py
tangelo/algorithms/classical/tests/test_mp2_solver.py
tangelo/algorithms/projective/__init__.py
tangelo/algorithms/projective/iqpe.py
tangelo/algorithms/projective/qpe.py
tangelo/algorithms/projective/quantum_imaginary_time.py
tangelo/algorithms/projective/tests/__init__.py
tangelo/algorithms/projective/tests/test_iqpe.py
tangelo/algorithms/projective/tests/test_qite.py
tangelo/algorithms/projective/tests/test_qpe.py
tangelo/algorithms/variational/__init__.py
tangelo/algorithms/variational/adapt_vqe_solver.py
tangelo/algorithms/variational/iqcc_ilc_solver.py
tangelo/algorithms/variational/iqcc_solver.py
tangelo/algorithms/variational/sa_oo_vqe_solver.py
tangelo/algorithms/variational/sa_vqe_solver.py
tangelo/algorithms/variational/tetris_adapt_vqe_solver.py
tangelo/algorithms/variational/vqe_solver.py
tangelo/algorithms/variational/tests/__init__.py
tangelo/algorithms/variational/tests/test_adapt_vqe_solver.py
tangelo/algorithms/variational/tests/test_iqcc_ilc_solver.py
tangelo/algorithms/variational/tests/test_iqcc_solver.py
tangelo/algorithms/variational/tests/test_sa_oo_vqe_solver.py
tangelo/algorithms/variational/tests/test_sa_vqe_solver.py
tangelo/algorithms/variational/tests/test_tetris_adapt_vqe_solver.py
tangelo/algorithms/variational/tests/test_vqe_solver.py
tangelo/helpers/__init__.py
tangelo/helpers/math.py
tangelo/helpers/utils.py
tangelo/linq/__init__.py
tangelo/linq/circuit.py
tangelo/linq/gate.py
tangelo/linq/qdk_template.py
tangelo/linq/simulator.py
tangelo/linq/helpers/__init__.py
tangelo_gc-0.4.3.dist-info/LICENSE
tangelo_gc-0.4.3.dist-info/METADATA
tangelo_gc-0.4.3.dist-info/WHEEL
tangelo_gc-0.4.3.dist-info/top_level.txt
tangelo_gc-0.4.3.dist-info/RECORD
